screenium-0.2.0.dist-info/METADATA
screenium-0.2.0.dist-info/WHEEL
screenium-0.2.0.dist-info/entry_points.txt
screenium/__init__.py
screenium/draw.py
screenium/locator.py
screenium-0.2.0.dist-info/RECORD
