Metadata-Version: 2.1
Name: screenium
Version: 0.2.0
Summary: Like Selenium, but for your entire screen. Find and interact with text anywhere using OCR.
Author-Email: Yaser Martinez Palenzuela <yaser.martinez@gmail.com>
License: MIT
Requires-Python: >=3.9
Requires-Dist: colour>=0.1.5
Requires-Dist: mss>=10.0.0
Requires-Dist: pyobjc-framework-vision>=10.3.1
Requires-Dist: pyobjc-framework-cocoa>=10.3.1
Requires-Dist: pyobjc-framework-applicationservices>=10.3.1
Requires-Dist: pytest>=8.3.3
Requires-Dist: pynput>=1.7.7
Requires-Dist: pillow>=11.0.0
Requires-Dist: numpy>=2.0.2
